<?xml version="1.0" encoding="UTF-8"?>
<!--
Created with Funkin Packer v0.1.3 https://neeeoo.github.io/funkin-packer/
-->
<TextureAtlas imagePath="icon-bf.png" width="2586" height="116">
	<SubTexture name="fromLosing instance 10000" x="2315" y="1" width="136" height="108" frameX="-13" frameY="-3" frameWidth="159" frameHeight="114"/>
	<SubTexture name="fromLosing instance 10001" x="2315" y="1" width="136" height="108" frameX="-13" frameY="-3" frameWidth="159" frameHeight="114"/>
	<SubTexture name="fromLosing instance 10002" x="2454" y="1" width="131" height="114" frameX="-15" frameY="-0" frameWidth="159" frameHeight="114"/>
	<SubTexture name="fromLosing instance 10003" x="2454" y="1" width="131" height="114" frameX="-15" frameY="-0" frameWidth="159" frameHeight="114"/>
	<SubTexture name="fromLosing instance 10004" x="1417" y="1" width="155" height="102" frameX="-2" frameY="-2" frameWidth="159" frameHeight="114"/>
	<SubTexture name="fromLosing instance 10005" x="1417" y="1" width="155" height="102" frameX="-2" frameY="-2" frameWidth="159" frameHeight="114"/>
	<SubTexture name="fromLosing instance 10006" x="636" y="1" width="159" height="98" frameX="-0" frameY="-4" frameWidth="159" frameHeight="114"/>
	<SubTexture name="fromLosing instance 10007" x="636" y="1" width="159" height="98" frameX="-0" frameY="-4" frameWidth="159" frameHeight="114"/>
	<SubTexture name="fromLosing instance 10008" x="636" y="1" width="159" height="98" frameX="-0" frameY="-4" frameWidth="159" frameHeight="114"/>
	<SubTexture name="fromLosing instance 10009" x="636" y="1" width="159" height="98" frameX="-0" frameY="-4" frameWidth="159" frameHeight="114"/>
	<SubTexture name="fromWinning instance 10000" x="798" y="1" width="150" height="98" frameX="-3" frameY="-3" frameWidth="162" frameHeight="104"/>
	<SubTexture name="fromWinning instance 10001" x="798" y="1" width="150" height="98" frameX="-3" frameY="-3" frameWidth="162" frameHeight="104"/>
	<SubTexture name="fromWinning instance 10002" x="1" y="1" width="156" height="92" frameX="-0" frameY="-6" frameWidth="162" frameHeight="104"/>
	<SubTexture name="fromWinning instance 10003" x="1" y="1" width="156" height="92" frameX="-0" frameY="-6" frameWidth="162" frameHeight="104"/>
	<SubTexture name="fromWinning instance 10004" x="1732" y="1" width="154" height="103" frameX="-5" frameY="-0" frameWidth="162" frameHeight="104"/>
	<SubTexture name="fromWinning instance 10005" x="1732" y="1" width="154" height="103" frameX="-5" frameY="-0" frameWidth="162" frameHeight="104"/>
	<SubTexture name="fromWinning instance 10006" x="473" y="1" width="160" height="97" frameX="-2" frameY="-3" frameWidth="162" frameHeight="104"/>
	<SubTexture name="fromWinning instance 10007" x="473" y="1" width="160" height="97" frameX="-2" frameY="-3" frameWidth="162" frameHeight="104"/>
	<SubTexture name="fromWinning instance 10008" x="473" y="1" width="160" height="97" frameX="-2" frameY="-3" frameWidth="162" frameHeight="104"/>
	<SubTexture name="fromWinning instance 10009" x="473" y="1" width="160" height="97" frameX="-2" frameY="-3" frameWidth="162" frameHeight="104"/>
	<SubTexture name="idle instance 10000" x="951" y="1" width="158" height="98" frameX="-0" frameY="-3" frameWidth="158" frameHeight="103"/>
	<SubTexture name="idle instance 10001" x="951" y="1" width="158" height="98" frameX="-0" frameY="-3" frameWidth="158" frameHeight="103"/>
	<SubTexture name="idle instance 10002" x="1417" y="1" width="155" height="102" frameX="-1" frameY="-1" frameWidth="158" frameHeight="103"/>
	<SubTexture name="idle instance 10003" x="1417" y="1" width="155" height="102" frameX="-1" frameY="-1" frameWidth="158" frameHeight="103"/>
	<SubTexture name="idle instance 10004" x="1575" y="1" width="154" height="102" frameX="-2" frameY="-1" frameWidth="158" frameHeight="103"/>
	<SubTexture name="idle instance 10005" x="1575" y="1" width="154" height="102" frameX="-2" frameY="-1" frameWidth="158" frameHeight="103"/>
	<SubTexture name="idle instance 10006" x="1575" y="1" width="154" height="102" frameX="-2" frameY="-1" frameWidth="158" frameHeight="103"/>
	<SubTexture name="idle instance 10007" x="1575" y="1" width="154" height="102" frameX="-2" frameY="-1" frameWidth="158" frameHeight="103"/>
	<SubTexture name="idle instance 10008" x="1575" y="1" width="154" height="102" frameX="-2" frameY="-1" frameWidth="158" frameHeight="103"/>
	<SubTexture name="idle instance 10009" x="1575" y="1" width="154" height="102" frameX="-2" frameY="-1" frameWidth="158" frameHeight="103"/>
	<SubTexture name="losing instance 10000" x="2037" y="1" width="136" height="107" frameX="-3" frameY="-0" frameWidth="140" frameHeight="108"/>
	<SubTexture name="losing instance 10001" x="2037" y="1" width="136" height="107" frameX="-3" frameY="-0" frameWidth="140" frameHeight="108"/>
	<SubTexture name="losing instance 10002" x="2176" y="1" width="136" height="107" frameX="-3" frameY="-0" frameWidth="140" frameHeight="108"/>
	<SubTexture name="losing instance 10003" x="2176" y="1" width="136" height="107" frameX="-3" frameY="-0" frameWidth="140" frameHeight="108"/>
	<SubTexture name="toLosing instance 10000" x="1417" y="1" width="155" height="102" frameX="-2" frameY="-2" frameWidth="159" frameHeight="114"/>
	<SubTexture name="toLosing instance 10001" x="1417" y="1" width="155" height="102" frameX="-2" frameY="-2" frameWidth="159" frameHeight="114"/>
	<SubTexture name="toLosing instance 10002" x="636" y="1" width="159" height="98" frameX="-0" frameY="-4" frameWidth="159" frameHeight="114"/>
	<SubTexture name="toLosing instance 10003" x="636" y="1" width="159" height="98" frameX="-0" frameY="-4" frameWidth="159" frameHeight="114"/>
	<SubTexture name="toLosing instance 10004" x="2454" y="1" width="131" height="114" frameX="-15" frameY="-0" frameWidth="159" frameHeight="114"/>
	<SubTexture name="toLosing instance 10005" x="2454" y="1" width="131" height="114" frameX="-15" frameY="-0" frameWidth="159" frameHeight="114"/>
	<SubTexture name="toLosing instance 10006" x="2315" y="1" width="136" height="108" frameX="-13" frameY="-3" frameWidth="159" frameHeight="114"/>
	<SubTexture name="toLosing instance 10007" x="2315" y="1" width="136" height="108" frameX="-13" frameY="-3" frameWidth="159" frameHeight="114"/>
	<SubTexture name="toLosing instance 10008" x="2315" y="1" width="136" height="108" frameX="-13" frameY="-3" frameWidth="159" frameHeight="114"/>
	<SubTexture name="toLosing instance 10009" x="2315" y="1" width="136" height="108" frameX="-13" frameY="-3" frameWidth="159" frameHeight="114"/>
	<SubTexture name="toWinning instance 10000" x="1889" y="1" width="145" height="105" frameX="-16" frameY="-0" frameWidth="165" frameHeight="107"/>
	<SubTexture name="toWinning instance 10001" x="1889" y="1" width="145" height="105" frameX="-16" frameY="-0" frameWidth="165" frameHeight="107"/>
	<SubTexture name="toWinning instance 10002" x="317" y="1" width="153" height="95" frameX="-12" frameY="-5" frameWidth="165" frameHeight="107"/>
	<SubTexture name="toWinning instance 10003" x="317" y="1" width="153" height="95" frameX="-12" frameY="-5" frameWidth="165" frameHeight="107"/>
	<SubTexture name="toWinning instance 10004" x="1" y="1" width="156" height="92" frameX="-0" frameY="-11" frameWidth="165" frameHeight="107"/>
	<SubTexture name="toWinning instance 10005" x="1" y="1" width="156" height="92" frameX="-0" frameY="-11" frameWidth="165" frameHeight="107"/>
	<SubTexture name="toWinning instance 10006" x="798" y="1" width="150" height="98" frameX="-3" frameY="-8" frameWidth="165" frameHeight="107"/>
	<SubTexture name="toWinning instance 10007" x="798" y="1" width="150" height="98" frameX="-3" frameY="-8" frameWidth="165" frameHeight="107"/>
	<SubTexture name="toWinning instance 10008" x="798" y="1" width="150" height="98" frameX="-3" frameY="-8" frameWidth="165" frameHeight="107"/>
	<SubTexture name="toWinning instance 10009" x="798" y="1" width="150" height="98" frameX="-3" frameY="-8" frameWidth="165" frameHeight="107"/>
	<SubTexture name="toWinning instance 20000" x="1889" y="1" width="145" height="105" frameX="-16" frameY="-0" frameWidth="165" frameHeight="107"/>
	<SubTexture name="toWinning instance 20001" x="1889" y="1" width="145" height="105" frameX="-16" frameY="-0" frameWidth="165" frameHeight="107"/>
	<SubTexture name="toWinning instance 20002" x="317" y="1" width="153" height="95" frameX="-12" frameY="-5" frameWidth="165" frameHeight="107"/>
	<SubTexture name="toWinning instance 20003" x="317" y="1" width="153" height="95" frameX="-12" frameY="-5" frameWidth="165" frameHeight="107"/>
	<SubTexture name="toWinning instance 20004" x="1" y="1" width="156" height="92" frameX="-0" frameY="-11" frameWidth="165" frameHeight="107"/>
	<SubTexture name="toWinning instance 20005" x="1" y="1" width="156" height="92" frameX="-0" frameY="-11" frameWidth="165" frameHeight="107"/>
	<SubTexture name="toWinning instance 20006" x="798" y="1" width="150" height="98" frameX="-3" frameY="-8" frameWidth="165" frameHeight="107"/>
	<SubTexture name="toWinning instance 20007" x="798" y="1" width="150" height="98" frameX="-3" frameY="-8" frameWidth="165" frameHeight="107"/>
	<SubTexture name="toWinning instance 20008" x="798" y="1" width="150" height="98" frameX="-3" frameY="-8" frameWidth="165" frameHeight="107"/>
	<SubTexture name="toWinning instance 20009" x="798" y="1" width="150" height="98" frameX="-3" frameY="-8" frameWidth="165" frameHeight="107"/>
	<SubTexture name="winning instance 10000" x="160" y="1" width="154" height="94" frameX="-0" frameY="-3" frameWidth="154" frameHeight="99"/>
	<SubTexture name="winning instance 10001" x="160" y="1" width="154" height="94" frameX="-0" frameY="-3" frameWidth="154" frameHeight="99"/>
	<SubTexture name="winning instance 10002" x="1112" y="1" width="150" height="98" frameX="-2" frameY="-1" frameWidth="154" frameHeight="99"/>
	<SubTexture name="winning instance 10003" x="1112" y="1" width="150" height="98" frameX="-2" frameY="-1" frameWidth="154" frameHeight="99"/>
	<SubTexture name="winning instance 10004" x="1265" y="1" width="149" height="98" frameX="-2" frameY="-1" frameWidth="154" frameHeight="99"/>
	<SubTexture name="winning instance 10005" x="1265" y="1" width="149" height="98" frameX="-2" frameY="-1" frameWidth="154" frameHeight="99"/>
	<SubTexture name="winning instance 10006" x="1265" y="1" width="149" height="98" frameX="-2" frameY="-1" frameWidth="154" frameHeight="99"/>
	<SubTexture name="winning instance 10007" x="1265" y="1" width="149" height="98" frameX="-2" frameY="-1" frameWidth="154" frameHeight="99"/>
	<SubTexture name="winning instance 10008" x="1265" y="1" width="149" height="98" frameX="-2" frameY="-1" frameWidth="154" frameHeight="99"/>
	<SubTexture name="winning instance 10009" x="1265" y="1" width="149" height="98" frameX="-2" frameY="-1" frameWidth="154" frameHeight="99"/>
</TextureAtlas>